pyesios/ESIOS.py
pyesios/__init__.py
pyesios/__version__.py
pyesios/utils.py
pyesios-0.1.3.dist-info/LICENSE.txt
pyesios-0.1.3.dist-info/METADATA
pyesios-0.1.3.dist-info/WHEEL
pyesios-0.1.3.dist-info/RECORD
