Metadata-Version: 2.1
Name: pyesios
Version: 0.1.3
Summary: Access to the ESIOS data, the Spanish electricity market entity.
Home-page: https://github.com/SanPen/ESIOS
License: LICENSE.txt
Author: Santiago Peñate Vera
Author-email: santiago.penate.vera@gmail.com
Requires-Python: >=3.9,<4.0
Classifier: License :: Other/Proprietary License
Classifier: Programming Language :: Python :: 3
Classifier: Programming Language :: Python :: 3.9
Classifier: Programming Language :: Python :: 3.10
Classifier: Programming Language :: Python :: 3.11
Provides-Extra: graphs
Requires-Dist: matplotlib ; extra == "graphs"
Requires-Dist: numpy
Requires-Dist: pandas
Project-URL: Bug Tracker, https://github.com/SanPen/ESIOS/issues
Project-URL: Repository, https://github.com/SanPen/ESIOS
Project-URL: Source Code, https://github.com/SanPen/ESIOS
